bytedmemfd/__init__.py
bytedmemfdd345-0.2.dist-info/licenses/LICENSE
bytedmemfdd345-0.2.dist-info/METADATA
bytedmemfdd345-0.2.dist-info/WHEEL
bytedmemfdd345-0.2.dist-info/top_level.txt
bytedmemfdd345-0.2.dist-info/RECORD
