Metadata-Version: 2.4
Name: bytedmemfdd345
Version: 0.2
Summary: 吃枣药丸
Home-page: 
Author: xlzd
Author-email: tellmewhy@gmail.com
License-File: LICENSE
Dynamic: author
Dynamic: author-email
Dynamic: license-file
Dynamic: summary
